aircloudy/__about__.py
aircloudy/__init__.py
aircloudy/aircloud.py
aircloudy/api/__init__.py
aircloudy/api/auth_manager.py
aircloudy/api/command_state_monitor.py
aircloudy/api/http_client.py
aircloudy/api/http_client_models.py
aircloudy/api/iam.py
aircloudy/api/iam_models.py
aircloudy/api/rac.py
aircloudy/api/rac_models.py
aircloudy/contants.py
aircloudy/errors.py
aircloudy/interior_unit.py
aircloudy/interior_unit_base.py
aircloudy/interior_unit_changes.py
aircloudy/notifications/__init__.py
aircloudy/notifications/hitachi_frame_models.py
aircloudy/notifications/notifications_websocket.py
aircloudy/notifications/stomp/SPEC.txt
aircloudy/notifications/stomp/__init__.py
aircloudy/notifications/stomp/frames.py
aircloudy/notifications/stomp/frames_models.py
aircloudy/notifications/stomp/frames_server.py
aircloudy/notifications/stomp/frames_server_models.py
aircloudy/utils.py
aircloudy-0.1.14.dist-info/METADATA
aircloudy-0.1.14.dist-info/WHEEL
aircloudy-0.1.14.dist-info/licenses/LICENSE.txt
aircloudy-0.1.14.dist-info/RECORD
