Metadata-Version: 2.4
Name: aircloudy
Version: 0.1.14
Summary: A library to pilot hitachi aircloud AC
License-File: LICENSE.txt
Keywords: aircloud,SPX-WFG
Author: Yann Le Moigne
Author-email: ylemoigne@javatic.fr
Requires-Python: >=3.13
Classifier: Intended Audience :: Developers
Classifier: Programming Language :: Python :: 3
Classifier: Programming Language :: Python :: 3.14
Requires-Dist: aiodns (>=3.5.0,<4.0.0)
Requires-Dist: aiohttp (>=3.12.15,<4.0.0)
Requires-Dist: pyjwt (>=2.10.1,<3.0.0)
Requires-Dist: tzlocal (>=5.3.1,<6.0.0)
Requires-Dist: websockets (>=15.0.1,<16.0.0)
Project-URL: Homepage, https://github.com/ylemoigne/aircloudy
Project-URL: Repository, https://github.com/ylemoigne/aircloudy
